superds/__init__.py
superds/superlist.py
superds-0.1.0.dist-info/WHEEL
superds-0.1.0.dist-info/METADATA
superds-0.1.0.dist-info/RECORD
